pyba/Camera.py
pyba/CameraNetwork.py
pyba/config.py
pyba/plot.py
pyba/pyba.py
pyba/util.py
nely_pyba-0.13.1.dist-info/METADATA
nely_pyba-0.13.1.dist-info/WHEEL
nely_pyba-0.13.1.dist-info/top_level.txt
nely_pyba-0.13.1.dist-info/RECORD
