Metadata-Version: 2.1
Name: nely-pyba
Version: 0.13.1
Summary: Python Bundle Adjustment Routines
Home-page: https://github.com/NeLy-EPFL/PyBundleAdjustment
Author: Semih Günel
